gwmailpy/__init__.py
gwmailpy/gwmailpy.py
gwmailpy-1.0.0.dist-info/METADATA
gwmailpy-1.0.0.dist-info/WHEEL
gwmailpy-1.0.0.dist-info/top_level.txt
gwmailpy-1.0.0.dist-info/RECORD
