Metadata-Version: 2.1
Name: gwmailpy
Version: 1.0.0
Summary: A simple api wrapper for (temp-mail) mail.gw.
Home-page: https://github.com/jiroawesome/gwmailpy
Author: JiroDeveloper
Author-email: contact@jiroawesome.tech
License: MIT License
Keywords: temp-mail tempmail mail.gw
Classifier: Programming Language :: Python
Classifier: Programming Language :: Python :: 2
Classifier: Programming Language :: Python :: 2.7
Classifier: Programming Language :: Python :: 3
Classifier: Programming Language :: Python :: 3.5
Classifier: Programming Language :: Python :: 3.6
Classifier: Programming Language :: Python :: 3.7
Classifier: Programming Language :: Python :: 3.8
Classifier: Programming Language :: Python :: 3.9
Classifier: Programming Language :: Python :: 3.10
